README.rst
setup.py
src/hexagonit/__init__.py
src/hexagonit.socialbutton.egg-info/PKG-INFO
src/hexagonit.socialbutton.egg-info/SOURCES.txt
src/hexagonit.socialbutton.egg-info/dependency_links.txt
src/hexagonit.socialbutton.egg-info/entry_points.txt
src/hexagonit.socialbutton.egg-info/namespace_packages.txt
src/hexagonit.socialbutton.egg-info/not-zip-safe
src/hexagonit.socialbutton.egg-info/requires.txt
src/hexagonit.socialbutton.egg-info/top_level.txt
src/hexagonit/socialbutton/__init__.py
src/hexagonit/socialbutton/config.py
src/hexagonit/socialbutton/configure.zcml
src/hexagonit/socialbutton/data.py
src/hexagonit/socialbutton/interfaces.py
src/hexagonit/socialbutton/upgrades.py
src/hexagonit/socialbutton/upgrades.zcml
src/hexagonit/socialbutton/utility.py
src/hexagonit/socialbutton/vocabulary.py
src/hexagonit/socialbutton/Extensions/Install.py
src/hexagonit/socialbutton/adapter/__init__.py
src/hexagonit/socialbutton/adapter/configure.zcml
src/hexagonit/socialbutton/adapter/dollar.py
src/hexagonit/socialbutton/browser/__init__.py
src/hexagonit/socialbutton/browser/configure.zcml
src/hexagonit/socialbutton/browser/interfaces.py
src/hexagonit/socialbutton/browser/miscellaneous.py
src/hexagonit/socialbutton/browser/template.py
src/hexagonit/socialbutton/browser/viewlet.py
src/hexagonit/socialbutton/browser/static/facebook.gif
src/hexagonit/socialbutton/browser/static/google-plus.gif
src/hexagonit/socialbutton/browser/static/livejournal.gif
src/hexagonit/socialbutton/browser/static/moimir.gif
src/hexagonit/socialbutton/browser/static/twitter.gif
src/hexagonit/socialbutton/browser/static/vkontakte.gif
src/hexagonit/socialbutton/browser/templates/controlpanel.pt
src/hexagonit/socialbutton/browser/viewlets/social-buttons.pt
src/hexagonit/socialbutton/docs/CONTRIBUTORS.rst
src/hexagonit/socialbutton/docs/HISTORY.rst
src/hexagonit/socialbutton/docs/INSTALL.rst
src/hexagonit/socialbutton/docs/LICENSE.rst
src/hexagonit/socialbutton/docs/Makefile
src/hexagonit/socialbutton/docs/README.rst
src/hexagonit/socialbutton/docs/conf.py
src/hexagonit/socialbutton/docs/index.rst
src/hexagonit/socialbutton/docs/_static/.gitignore
src/hexagonit/socialbutton/locales/hexagonit.socialbutton.pot
src/hexagonit/socialbutton/locales/en/LC_MESSAGES/hexagonit.socialbutton.mo
src/hexagonit/socialbutton/locales/en/LC_MESSAGES/hexagonit.socialbutton.po
