Metadata-Version: 1.1
Name: hexagonit.socialbutton
Version: 0.11
Summary: Adds viewlets for embedding codes such as social buttons for Plone.
Home-page: http://www.hexagonit.fi
Author: Hexagon IT
Author-email: oss@hexagonit.fi
License: BSD
Platform: UNKNOWN
Classifier: Framework :: Plone
Classifier: Framework :: Plone :: 4.3
Classifier: License :: OSI Approved :: BSD License
Classifier: Programming Language :: Python
Classifier: Programming Language :: Python :: 2.7
